ChanlunCaopanshuVol1/README.md
ChanlunCaopanshuVol1/__init__.py
ChanlunCaopanshuVol1/__main__.py
ChanlunCaopanshuVol1/file.epub
ChanlunCaopanshuVol1/index.html
ChanlunCaopanshuVol1/css/__init__.py
ChanlunCaopanshuVol1/css/annotations.css
ChanlunCaopanshuVol1/css/main.css
ChanlunCaopanshuVol1/css/normalize.css
ChanlunCaopanshuVol1/css/popup.css
ChanlunCaopanshuVol1/font/__init__.py
ChanlunCaopanshuVol1/font/fontello.eot
ChanlunCaopanshuVol1/font/fontello.svg
ChanlunCaopanshuVol1/font/fontello.ttf
ChanlunCaopanshuVol1/font/fontello.woff
ChanlunCaopanshuVol1/img/__init__.py
ChanlunCaopanshuVol1/img/annotator-glyph-sprite.png
ChanlunCaopanshuVol1/img/annotator-icon-sprite.png
ChanlunCaopanshuVol1/img/apple-touch-icon.png
ChanlunCaopanshuVol1/img/cancelfullscreen.png
ChanlunCaopanshuVol1/img/close.png
ChanlunCaopanshuVol1/img/fullscreen.png
ChanlunCaopanshuVol1/img/loader.gif
ChanlunCaopanshuVol1/img/menu-icon.png
ChanlunCaopanshuVol1/img/save.png
ChanlunCaopanshuVol1/img/saved.png
ChanlunCaopanshuVol1/img/settings-s.png
ChanlunCaopanshuVol1/img/settings.png
ChanlunCaopanshuVol1/img/star.png
ChanlunCaopanshuVol1/js/__init__.py
ChanlunCaopanshuVol1/js/epub.js
ChanlunCaopanshuVol1/js/epub.min.js
ChanlunCaopanshuVol1/js/epub.min.map
ChanlunCaopanshuVol1/js/hooks.min.js
ChanlunCaopanshuVol1/js/hooks.min.map
ChanlunCaopanshuVol1/js/reader.js
ChanlunCaopanshuVol1/js/reader.js.map
ChanlunCaopanshuVol1/js/reader.min.js
ChanlunCaopanshuVol1/js/reader.min.map
ChanlunCaopanshuVol1/js/hooks/__init__.py
ChanlunCaopanshuVol1/js/hooks/extensions/__init__.py
ChanlunCaopanshuVol1/js/hooks/extensions/highlight.js
ChanlunCaopanshuVol1/js/libs/__init__.py
ChanlunCaopanshuVol1/js/libs/jquery.min.js
ChanlunCaopanshuVol1/js/libs/localforage.min.js
ChanlunCaopanshuVol1/js/libs/screenfull.js
ChanlunCaopanshuVol1/js/libs/screenfull.min.js
ChanlunCaopanshuVol1/js/libs/zip.min.js
ChanlunCaopanshuVol1/js/plugins/__init__.py
ChanlunCaopanshuVol1/js/plugins/hypothesis.js
chanlun_caopanshu_vol1-2022.10.15.0.dist-info/METADATA
chanlun_caopanshu_vol1-2022.10.15.0.dist-info/WHEEL
chanlun_caopanshu_vol1-2022.10.15.0.dist-info/entry_points.txt
chanlun_caopanshu_vol1-2022.10.15.0.dist-info/top_level.txt
chanlun_caopanshu_vol1-2022.10.15.0.dist-info/RECORD
